MANIFEST.in
README.md
requirements-dev.txt
requirements.txt
setup.py
cgadmin/__init__.py
cgadmin/cli.py
cgadmin/constants.py
cgadmin/lims.py
cgadmin/log.py
cgadmin/orderform.py
cgadmin/schema.py
cgadmin.egg-info/PKG-INFO
cgadmin.egg-info/SOURCES.txt
cgadmin.egg-info/dependency_links.txt
cgadmin.egg-info/entry_points.txt
cgadmin.egg-info/not-zip-safe
cgadmin.egg-info/requires.txt
cgadmin.egg-info/top_level.txt
cgadmin/invoice/__init__.py
cgadmin/invoice/cli.py
cgadmin/invoice/render.py
cgadmin/invoice/templates/invoice.xlsx
cgadmin/report/__init__.py
cgadmin/report/core.py
cgadmin/report/templates/bootstrap.html
cgadmin/report/templates/report.html
cgadmin/server/__init__.py
cgadmin/server/admin.py
cgadmin/server/app.py
cgadmin/server/flask_sqlservice.py
cgadmin/server/mailgun.py
cgadmin/server/publicbp/__init__.py
cgadmin/server/publicbp/views.py
cgadmin/store/__init__.py
cgadmin/store/api.py
cgadmin/store/models.py
cgadmin/store/parse.py