Metadata-Version: 1.0
Name: cgadmin
Version: 1.0.2
Summary: Admin interface and order portal
Home-page: https://github.com/Clinical-Genomics/cgadmin
Author: Robin Andeer
Author-email: robin.andeer@scilifelab.se
License: MIP
Platform: UNKNOWN
